Metadata-Version: 2.1
Name: django-admin-resumable2
Version: 0.1
Summary: A Django app for the uploading of large files from the django admin site.
Home-page: https://github.com/rjnp2/django-admin-resumable2
Author: rjnp2
Author-email: rjnp2@outlook.com
License: MIT License
Platform: UNKNOWN
Classifier: Environment :: Web Environment
Classifier: Framework :: Django
Classifier: Intended Audience :: Developers
Classifier: License :: OSI Approved :: MIT License
Classifier: Operating System :: OS Independent
Classifier: Programming Language :: Python
Classifier: Programming Language :: Python :: 3.10
Classifier: Topic :: Internet :: WWW/HTTP
Classifier: Topic :: Internet :: WWW/HTTP :: Dynamic Content
Requires-Python: >=3.8
License-File: LICENSE
Provides-Extra: dev
Requires-Dist: twine (>=4.0.2) ; extra == 'dev'
